image_israel/__init__.py
image_israel/processing/__init__.py
image_israel/processing/combination.py
image_israel/processing/transformation.py
image_israel/utils/__init__.py
image_israel/utils/io.py
image_israel/utils/plot.py
image_israel-0.0.5.dist-info/METADATA
image_israel-0.0.5.dist-info/WHEEL
image_israel-0.0.5.dist-info/top_level.txt
image_israel-0.0.5.dist-info/RECORD
