Metadata-Version: 2.1
Name: image-israel
Version: 0.0.5
Summary: Pacote criado para processamento de imagem, a partir do curso de criação de pacotes da DIO
Home-page: https://github.com/israelclaudio/image_processing_package
Author: israelclaudio
Author-email: israelclaudio21@gmail.com
Requires-Python: >=3.8
Requires-Dist: matplotlib
Requires-Dist: numpy
Requires-Dist: scikit-image (>=0.16.1)
